shhhinterrupt/__init__.py
shhhinterrupt/main.py
shhhinterrupt-0.1.0.dist-info/METADATA
shhhinterrupt-0.1.0.dist-info/WHEEL
shhhinterrupt-0.1.0.dist-info/RECORD
